there_is_a_cve/__init__.py
there_is_a_cve/main.py
there_is_a_cve-0.1.2.dist-info/METADATA
there_is_a_cve-0.1.2.dist-info/WHEEL
there_is_a_cve-0.1.2.dist-info/entry_points.txt
there_is_a_cve-0.1.2.dist-info/top_level.txt
there_is_a_cve-0.1.2.dist-info/RECORD
