Metadata-Version: 2.1
Name: there-is-a-cve
Version: 0.1.2
Summary: A pentesting tool leveraging Shodan to identify vulnerabilities in internet-connected devices.
Home-page: https://github.com/activiste/THERE-IS-A-CVE
Author: Sparked
Author-email: sparked@onionmail.org
License: MIT
Classifier: Programming Language :: Python :: 3
Classifier: License :: OSI Approved :: MIT License
Classifier: Operating System :: POSIX :: Linux
Requires-Python: >=3.6
Requires-Dist: requests
Requires-Dist: beautifulsoup4
Requires-Dist: dnspython
Requires-Dist: tabulate
Requires-Dist: inquirer
